opencmiss.zinc-3.10.2.data/purelib/opencmiss/__init__.py
opencmiss.zinc-3.10.2.data/purelib/opencmiss/zinc/__init__.py
opencmiss.zinc-3.10.2.data/purelib/opencmiss/zinc/_context.pyd
opencmiss.zinc-3.10.2.data/purelib/opencmiss/zinc/_differentialoperator.pyd
opencmiss.zinc-3.10.2.data/purelib/opencmiss/zinc/_element.pyd
opencmiss.zinc-3.10.2.data/purelib/opencmiss/zinc/_field.pyd
opencmiss.zinc-3.10.2.data/purelib/opencmiss/zinc/_fieldassignment.pyd
opencmiss.zinc-3.10.2.data/purelib/opencmiss/zinc/_fieldcache.pyd
opencmiss.zinc-3.10.2.data/purelib/opencmiss/zinc/_fieldmodule.pyd
opencmiss.zinc-3.10.2.data/purelib/opencmiss/zinc/_fieldparameters.pyd
opencmiss.zinc-3.10.2.data/purelib/opencmiss/zinc/_fieldrange.pyd
opencmiss.zinc-3.10.2.data/purelib/opencmiss/zinc/_fieldsmoothing.pyd
opencmiss.zinc-3.10.2.data/purelib/opencmiss/zinc/_font.pyd
opencmiss.zinc-3.10.2.data/purelib/opencmiss/zinc/_glyph.pyd
opencmiss.zinc-3.10.2.data/purelib/opencmiss/zinc/_graphics.pyd
opencmiss.zinc-3.10.2.data/purelib/opencmiss/zinc/_light.pyd
opencmiss.zinc-3.10.2.data/purelib/opencmiss/zinc/_logger.pyd
opencmiss.zinc-3.10.2.data/purelib/opencmiss/zinc/_material.pyd
opencmiss.zinc-3.10.2.data/purelib/opencmiss/zinc/_node.pyd
opencmiss.zinc-3.10.2.data/purelib/opencmiss/zinc/_optimisation.pyd
opencmiss.zinc-3.10.2.data/purelib/opencmiss/zinc/_region.pyd
opencmiss.zinc-3.10.2.data/purelib/opencmiss/zinc/_result.pyd
opencmiss.zinc-3.10.2.data/purelib/opencmiss/zinc/_scene.pyd
opencmiss.zinc-3.10.2.data/purelib/opencmiss/zinc/_scenecoordinatesystem.pyd
opencmiss.zinc-3.10.2.data/purelib/opencmiss/zinc/_scenefilter.pyd
opencmiss.zinc-3.10.2.data/purelib/opencmiss/zinc/_scenepicker.pyd
opencmiss.zinc-3.10.2.data/purelib/opencmiss/zinc/_sceneviewer.pyd
opencmiss.zinc-3.10.2.data/purelib/opencmiss/zinc/_sceneviewerinput.pyd
opencmiss.zinc-3.10.2.data/purelib/opencmiss/zinc/_selection.pyd
opencmiss.zinc-3.10.2.data/purelib/opencmiss/zinc/_shader.pyd
opencmiss.zinc-3.10.2.dist-info/LICENSE.txt
opencmiss.zinc-3.10.2.dist-info/METADATA
opencmiss.zinc-3.10.2.dist-info/WHEEL
opencmiss.zinc-3.10.2.dist-info/top_level.txt
opencmiss.zinc-3.10.2.dist-info/RECORD
